BlaApi/__init__.py
BlaApi/client.py
BlaApi-2.1.dist-info/LICENSE
BlaApi-2.1.dist-info/METADATA
BlaApi-2.1.dist-info/WHEEL
BlaApi-2.1.dist-info/top_level.txt
BlaApi-2.1.dist-info/RECORD
