Metadata-Version: 2.1
Name: BlaApi
Version: 2.1
Summary: A wrapper for the beacon light api.
Home-page: https://github.com/me/myproject
Author: Omer-Farooqui
Author-email: deaddogfuneral@gmail.com
License: BSD-4
Classifier: License :: OSI Approved :: BSD License
Classifier: Programming Language :: Python
Classifier: Programming Language :: Python :: 3
Classifier: Programming Language :: Python :: 3.7
Classifier: Programming Language :: Python :: Implementation :: CPython
Classifier: Programming Language :: Python :: Implementation :: PyPy
Requires-Python: >=3.7.0
License-File: LICENSE
Requires-Dist: httpx
Requires-Dist: fake-useragent
Requires-Dist: markdownify
